Metadata-Version: 2.1
Name: odoo-addon-l10n_fr_account_vat_return_teledec
Version: 16.0.3.0.0.4
Summary: Teletransmit CA3 via Teledec.fr (subscription required)
Home-page: https://github.com/OCA/l10n-france
Author: Akretion,Odoo Community Association (OCA)
Author-email: support@odoo-community.org
License: AGPL-3
Classifier: Programming Language :: Python
Classifier: Framework :: Odoo
Classifier: Framework :: Odoo :: 16.0
Classifier: License :: OSI Approved :: GNU Affero General Public License v3
Requires-Python: >=3.10
Requires-Dist: odoo-addon-l10n-fr-account-vat-return<16.1dev,>=16.0dev
Requires-Dist: odoo<16.1dev,>=16.0a
Requires-Dist: requests
